grafeas/__init__.py
grafeas/grafeas/__init__.py
grafeas/grafeas/gapic_version.py
grafeas/grafeas/py.typed
grafeas/grafeas_v1/__init__.py
grafeas/grafeas_v1/gapic_metadata.json
grafeas/grafeas_v1/gapic_version.py
grafeas/grafeas_v1/py.typed
grafeas/grafeas_v1/types.py
grafeas/grafeas_v1/services/__init__.py
grafeas/grafeas_v1/services/grafeas/__init__.py
grafeas/grafeas_v1/services/grafeas/async_client.py
grafeas/grafeas_v1/services/grafeas/client.py
grafeas/grafeas_v1/services/grafeas/pagers.py
grafeas/grafeas_v1/services/grafeas/transports/__init__.py
grafeas/grafeas_v1/services/grafeas/transports/base.py
grafeas/grafeas_v1/services/grafeas/transports/grpc.py
grafeas/grafeas_v1/services/grafeas/transports/grpc_asyncio.py
grafeas/grafeas_v1/services/grafeas/transports/rest.py
grafeas/grafeas_v1/services/grafeas/transports/rest_base.py
grafeas/grafeas_v1/types/__init__.py
grafeas/grafeas_v1/types/attestation.py
grafeas/grafeas_v1/types/build.py
grafeas/grafeas_v1/types/common.py
grafeas/grafeas_v1/types/compliance.py
grafeas/grafeas_v1/types/cvss.py
grafeas/grafeas_v1/types/deployment.py
grafeas/grafeas_v1/types/discovery.py
grafeas/grafeas_v1/types/dsse_attestation.py
grafeas/grafeas_v1/types/grafeas.py
grafeas/grafeas_v1/types/image.py
grafeas/grafeas_v1/types/intoto_provenance.py
grafeas/grafeas_v1/types/intoto_statement.py
grafeas/grafeas_v1/types/package.py
grafeas/grafeas_v1/types/provenance.py
grafeas/grafeas_v1/types/risk.py
grafeas/grafeas_v1/types/sbom.py
grafeas/grafeas_v1/types/secret.py
grafeas/grafeas_v1/types/severity.py
grafeas/grafeas_v1/types/slsa_provenance.py
grafeas/grafeas_v1/types/slsa_provenance_zero_two.py
grafeas/grafeas_v1/types/upgrade.py
grafeas/grafeas_v1/types/vex.py
grafeas/grafeas_v1/types/vulnerability.py
grafeas-1.19.0.dist-info/licenses/LICENSE
grafeas-1.19.0.dist-info/METADATA
grafeas-1.19.0.dist-info/WHEEL
grafeas-1.19.0.dist-info/top_level.txt
grafeas-1.19.0.dist-info/RECORD
